dynmap_png/__init__.py
dynmap_png/coords.py
dynmap_png/dynmap.py
dynmap_png/imager.py
dynmap_png-0.2.0.dist-info/LICENSE
dynmap_png-0.2.0.dist-info/METADATA
dynmap_png-0.2.0.dist-info/WHEEL
dynmap_png-0.2.0.dist-info/entry_points.txt
dynmap_png-0.2.0.dist-info/top_level.txt
dynmap_png-0.2.0.dist-info/RECORD
